{
  "missions": [
    {"id": 1, "difficulty": "easy", "demon": "Shadow Wraith", "xp_reward": 50, "gold_reward": 75, "boss": false},
    {"id": 2, "difficulty": "easy", "demon": "Forest Beast", "xp_reward": 55, "gold_reward": 80, "boss": false},
    {"id": 3, "difficulty": "easy", "demon": "Night Terror", "xp_reward": 60, "gold_reward": 90, "boss": false},
    {"id": 4, "difficulty": "easy", "demon": "Blood Hungry Demon", "xp_reward": 70, "gold_reward": 100, "boss": false},
    {"id": 5, "difficulty": "easy", "demon": "Stone Guardian", "xp_reward": 75, "gold_reward": 110, "boss": false},
    {"id": 6, "difficulty": "easy", "demon": "Shadow Wraith", "xp_reward": 50, "gold_reward": 75, "boss": false},
    {"id": 7, "difficulty": "easy", "demon": "Forest Beast", "xp_reward": 55, "gold_reward": 80, "boss": false},
    {"id": 8, "difficulty": "easy", "demon": "Crimson Shade", "xp_reward": 85, "gold_reward": 125, "boss": false},
    {"id": 9, "difficulty": "easy", "demon": "Night Terror", "xp_reward": 60, "gold_reward": 90, "boss": false},
    {"id": 10, "difficulty": "easy", "demon": "Void Creature", "xp_reward": 95, "gold_reward": 140, "boss": false},
    {"id": 11, "difficulty": "easy", "demon": "Blood Hungry Demon", "xp_reward": 70, "gold_reward": 100, "boss": false},
    {"id": 12, "difficulty": "easy", "demon": "Shadow Wraith", "xp_reward": 50, "gold_reward": 75, "boss": false},
    {"id": 13, "difficulty": "easy", "demon": "Stone Guardian", "xp_reward": 75, "gold_reward": 110, "boss": false},
    {"id": 14, "difficulty": "easy", "demon": "Crimson Shade", "xp_reward": 85, "gold_reward": 125, "boss": false},
    {"id": 15, "difficulty": "easy", "demon": "Forest Beast", "xp_reward": 55, "gold_reward": 80, "boss": false},
    {"id": 16, "difficulty": "easy", "demon": "Infernal Beast", "xp_reward": 110, "gold_reward": 160, "boss": false},
    {"id": 17, "difficulty": "easy", "demon": "Night Terror", "xp_reward": 60, "gold_reward": 90, "boss": false},
    {"id": 18, "difficulty": "easy", "demon": "Void Creature", "xp_reward": 95, "gold_reward": 140, "boss": false},
    {"id": 19, "difficulty": "easy", "demon": "Blood Hungry Demon", "xp_reward": 70, "gold_reward": 100, "boss": false},
    {"id": 20, "difficulty": "easy", "demon": "Stone Guardian", "xp_reward": 75, "gold_reward": 110, "boss": false},
    {"id": 21, "difficulty": "easy", "demon": "Shadow Wraith", "xp_reward": 50, "gold_reward": 75, "boss": false},
    {"id": 22, "difficulty": "easy", "demon": "Phantom Lord", "xp_reward": 130, "gold_reward": 200, "boss": false},
    {"id": 23, "difficulty": "easy", "demon": "Forest Beast", "xp_reward": 55, "gold_reward": 80, "boss": false},
    {"id": 24, "difficulty": "easy", "demon": "Crimson Shade", "xp_reward": 85, "gold_reward": 125, "boss": false},
    {"id": 25, "difficulty": "easy", "demon": "Lower Moon 6 (Kamanue)", "xp_reward": 100, "gold_reward": 150, "boss": false},
    {"id": 26, "difficulty": "easy", "demon": "Night Terror", "xp_reward": 60, "gold_reward": 90, "boss": false},
    {"id": 27, "difficulty": "easy", "demon": "Void Creature", "xp_reward": 95, "gold_reward": 140, "boss": false},
    {"id": 28, "difficulty": "easy", "demon": "Abyssal Warden", "xp_reward": 150, "gold_reward": 250, "boss": false},
    {"id": 29, "difficulty": "easy", "demon": "Blood Hungry Demon", "xp_reward": 70, "gold_reward": 100, "boss": false},
    {"id": 30, "difficulty": "easy", "demon": "Lower Moon 1 (Enmu)", "xp_reward": 300, "gold_reward": 500, "boss": true, "next_difficulty": "hard"},
    {"id": 31, "difficulty": "hard", "demon": "Lower Moon 5 (Rokuro)", "xp_reward": 120, "gold_reward": 200, "boss": false},
    {"id": 32, "difficulty": "hard", "demon": "Crimson Reaper", "xp_reward": 180, "gold_reward": 300, "boss": false},
    {"id": 33, "difficulty": "hard", "demon": "Twilight Wraith", "xp_reward": 200, "gold_reward": 350, "boss": false},
    {"id": 34, "difficulty": "hard", "demon": "Lower Moon 4 (Mukago)", "xp_reward": 150, "gold_reward": 250, "boss": false},
    {"id": 35, "difficulty": "hard", "demon": "Lower Moon 2 (Rui)", "xp_reward": 250, "gold_reward": 400, "boss": false},
    {"id": 36, "difficulty": "hard", "demon": "Eclipse Demon", "xp_reward": 220, "gold_reward": 400, "boss": false},
    {"id": 37, "difficulty": "hard", "demon": "Eternal Plague", "xp_reward": 250, "gold_reward": 450, "boss": false},
    {"id": 38, "difficulty": "hard", "demon": "Lower Moon 3 (Wakuraba)", "xp_reward": 200, "gold_reward": 300, "boss": false},
    {"id": 39, "difficulty": "hard", "demon": "Sovereign of Darkness", "xp_reward": 280, "gold_reward": 500, "boss": false},
    {"id": 40, "difficulty": "hard", "demon": "Twilight Wraith", "xp_reward": 200, "gold_reward": 350, "boss": false},
    {"id": 41, "difficulty": "hard", "demon": "Crimson Reaper", "xp_reward": 180, "gold_reward": 300, "boss": false},
    {"id": 42, "difficulty": "hard", "demon": "Eclipse Demon", "xp_reward": 220, "gold_reward": 400, "boss": false},
    {"id": 43, "difficulty": "hard", "demon": "Phantom Lord", "xp_reward": 130, "gold_reward": 200, "boss": false},
    {"id": 44, "difficulty": "hard", "demon": "Abyssal Warden", "xp_reward": 150, "gold_reward": 250, "boss": false},
    {"id": 45, "difficulty": "hard", "demon": "Upper Moon 6 (Gyutaro & Daki)", "xp_reward": 900, "gold_reward": 1900, "boss": true, "next_difficulty": "hard"},
    {"id": 46, "difficulty": "hard", "demon": "Eternal Plague", "xp_reward": 250, "gold_reward": 450, "boss": false},
    {"id": 47, "difficulty": "hard", "demon": "Sovereign of Darkness", "xp_reward": 280, "gold_reward": 500, "boss": false},
    {"id": 48, "difficulty": "hard", "demon": "Crimson Reaper", "xp_reward": 180, "gold_reward": 300, "boss": false},
    {"id": 49, "difficulty": "hard", "demon": "Twilight Wraith", "xp_reward": 200, "gold_reward": 350, "boss": false},
    {"id": 50, "difficulty": "hard", "demon": "Eclipse Demon", "xp_reward": 220, "gold_reward": 400, "boss": false},
    {"id": 51, "difficulty": "hard", "demon": "Void Creature", "xp_reward": 95, "gold_reward": 140, "boss": false},
    {"id": 52, "difficulty": "hard", "demon": "Phantom Lord", "xp_reward": 130, "gold_reward": 200, "boss": false},
    {"id": 53, "difficulty": "hard", "demon": "Crimson Reaper", "xp_reward": 180, "gold_reward": 300, "boss": false},
    {"id": 54, "difficulty": "hard", "demon": "Abyssal Warden", "xp_reward": 150, "gold_reward": 250, "boss": false},
    {"id": 55, "difficulty": "hard", "demon": "Upper Moon 5 (Gyokko)", "xp_reward": 1100, "gold_reward": 2100, "boss": true, "next_difficulty": "hard"},
    {"id": 56, "difficulty": "hard", "demon": "Eternal Plague", "xp_reward": 250, "gold_reward": 450, "boss": false},
    {"id": 57, "difficulty": "hard", "demon": "Sovereign of Darkness", "xp_reward": 280, "gold_reward": 500, "boss": false},
    {"id": 58, "difficulty": "hard", "demon": "Twilight Wraith", "xp_reward": 200, "gold_reward": 350, "boss": false},
    {"id": 59, "difficulty": "hard", "demon": "Eclipse Demon", "xp_reward": 220, "gold_reward": 400, "boss": false},
    {"id": 60, "difficulty": "hard", "demon": "Crimson Reaper", "xp_reward": 180, "gold_reward": 300, "boss": false},
    {"id": 61, "difficulty": "hard", "demon": "Phantom Lord", "xp_reward": 130, "gold_reward": 200, "boss": false},
    {"id": 62, "difficulty": "hard", "demon": "Abyssal Warden", "xp_reward": 150, "gold_reward": 250, "boss": false},
    {"id": 63, "difficulty": "hard", "demon": "Eternal Plague", "xp_reward": 250, "gold_reward": 450, "boss": false},
    {"id": 64, "difficulty": "hard", "demon": "Sovereign of Darkness", "xp_reward": 280, "gold_reward": 500, "boss": false},
    {"id": 65, "difficulty": "hard", "demon": "Upper Moon 4 (Hantengu)", "xp_reward": 1300, "gold_reward": 2300, "boss": true, "next_difficulty": "hard"},
    {"id": 66, "difficulty": "hard", "demon": "Twilight Wraith", "xp_reward": 200, "gold_reward": 350, "boss": false},
    {"id": 67, "difficulty": "hard", "demon": "Eclipse Demon", "xp_reward": 220, "gold_reward": 400, "boss": false},
    {"id": 68, "difficulty": "hard", "demon": "Crimson Reaper", "xp_reward": 180, "gold_reward": 300, "boss": false},
    {"id": 69, "difficulty": "hard", "demon": "Phantom Lord", "xp_reward": 130, "gold_reward": 200, "boss": false},
    {"id": 70, "difficulty": "hard", "demon": "Abyssal Warden", "xp_reward": 150, "gold_reward": 250, "boss": false},
    {"id": 71, "difficulty": "hard", "demon": "Eternal Plague", "xp_reward": 250, "gold_reward": 450, "boss": false},
    {"id": 72, "difficulty": "hard", "demon": "Sovereign of Darkness", "xp_reward": 280, "gold_reward": 500, "boss": false},
    {"id": 73, "difficulty": "hard", "demon": "Twilight Wraith", "xp_reward": 200, "gold_reward": 350, "boss": false},
    {"id": 74, "difficulty": "hard", "demon": "Eclipse Demon", "xp_reward": 220, "gold_reward": 400, "boss": false},
    {"id": 75, "difficulty": "hard", "demon": "Upper Moon 3 (Akaza)", "xp_reward": 1500, "gold_reward": 2500, "boss": true, "next_difficulty": "hell"},
    {"id": 76, "difficulty": "hell", "demon": "Void Emperor", "xp_reward": 350, "gold_reward": 700, "boss": false},
    {"id": 77, "difficulty": "hell", "demon": "Primordial Evil", "xp_reward": 380, "gold_reward": 800, "boss": false},
    {"id": 78, "difficulty": "hell", "demon": "Chaotic Force", "xp_reward": 320, "gold_reward": 600, "boss": false},
    {"id": 79, "difficulty": "hell", "demon": "Sovereign of Darkness", "xp_reward": 280, "gold_reward": 500, "boss": false},
    {"id": 80, "difficulty": "hell", "demon": "Void Emperor", "xp_reward": 350, "gold_reward": 700, "boss": false},
    {"id": 81, "difficulty": "hell", "demon": "Primordial Evil", "xp_reward": 380, "gold_reward": 800, "boss": false},
    {"id": 82, "difficulty": "hell", "demon": "Chaotic Force", "xp_reward": 320, "gold_reward": 600, "boss": false},
    {"id": 83, "difficulty": "hell", "demon": "Void Emperor", "xp_reward": 350, "gold_reward": 700, "boss": false},
    {"id": 84, "difficulty": "hell", "demon": "Primordial Evil", "xp_reward": 380, "gold_reward": 800, "boss": false},
    {"id": 85, "difficulty": "hell", "demon": "Upper Moon 2 (Doma)", "xp_reward": 1800, "gold_reward": 2800, "boss": true, "next_difficulty": "hell"},
    {"id": 86, "difficulty": "hell", "demon": "Chaotic Force", "xp_reward": 320, "gold_reward": 600, "boss": false},
    {"id": 87, "difficulty": "hell", "demon": "Void Emperor", "xp_reward": 350, "gold_reward": 700, "boss": false},
    {"id": 88, "difficulty": "hell", "demon": "Primordial Evil", "xp_reward": 380, "gold_reward": 800, "boss": false},
    {"id": 89, "difficulty": "hell", "demon": "Chaotic Force", "xp_reward": 320, "gold_reward": 600, "boss": false},
    {"id": 90, "difficulty": "hell", "demon": "Void Emperor", "xp_reward": 350, "gold_reward": 700, "boss": false},
    {"id": 91, "difficulty": "hell", "demon": "Primordial Evil", "xp_reward": 380, "gold_reward": 800, "boss": false},
    {"id": 92, "difficulty": "hell", "demon": "Chaotic Force", "xp_reward": 320, "gold_reward": 600, "boss": false},
    {"id": 93, "difficulty": "hell", "demon": "Void Emperor", "xp_reward": 350, "gold_reward": 700, "boss": false},
    {"id": 94, "difficulty": "hell", "demon": "Primordial Evil", "xp_reward": 380, "gold_reward": 800, "boss": false},
    {"id": 95, "difficulty": "hell", "demon": "Upper Moon 1 (Kokushibo)", "xp_reward": 2000, "gold_reward": 3000, "boss": true, "next_difficulty": "hell"},
    {"id": 96, "difficulty": "hell", "demon": "Primordial Evil", "xp_reward": 380, "gold_reward": 800, "boss": false},
    {"id": 97, "difficulty": "hell", "demon": "Chaotic Force", "xp_reward": 320, "gold_reward": 600, "boss": false},
    {"id": 98, "difficulty": "hell", "demon": "Void Emperor", "xp_reward": 350, "gold_reward": 700, "boss": false},
    {"id": 99, "difficulty": "hell", "demon": "Primordial Evil", "xp_reward": 380, "gold_reward": 800, "boss": false},
    {"id": 100, "difficulty": "hell", "demon": "Muzan Kibutsuji", "xp_reward": 5000, "gold_reward": 10000, "boss": true, "final": true}
  ]
}
